ratelimiteredis/__init__.py
ratelimiteredis/exceptions.py
ratelimiteredis/main.py
ratelimiteredis/redis.py
ratelimiteredis/utils.py
ratelimiteredis-0.1.23.dist-info/LICENSE
ratelimiteredis-0.1.23.dist-info/METADATA
ratelimiteredis-0.1.23.dist-info/WHEEL
ratelimiteredis-0.1.23.dist-info/top_level.txt
ratelimiteredis-0.1.23.dist-info/RECORD
